[
    {
        "id": 1,
        "email": "",
        "password": ""
    },
    {
        "id": 2,
        "email": "liam",
        "password": "$2a$08$euXIH5CLVXG2nlLhMovmGOje0NphULVeEWNsnUcYj30hmkyeBYEqG"
    },
    {
        "id": 3,
        "email": "ben",
        "password": "$2a$08$ncr1PuIWMH0NyBaYUtIjD.tvSxrgasA7LxMD0IUh.KTCh2BO7dMNy"
    },
    {
        "id": 4,
        "email": "test",
        "password": "$2a$08$I94OigwLj.3yTtBi8C67y.L84nKAfchQo9IX4zHitBVvBlAM637s2"
    },
    {
        "id": 5,
        "email": "a",
        "password": "$2a$08$Noz9O5GjPJPd0XPeXkRov.WVUgsIchvP7MMAYxUvuM4dDIGe6.n7a"
    },
    {
        "id": 6,
        "email": "william",
        "password": "$2a$08$pZ3MrBizJuHOrAEE3mkyMu37XlUMVdCNQDniFvJmySfq9lA0dvyiW"
    },
    {
        "id": 7,
        "email": "john",
        "password": "$2a$08$hQTxtfA8ZC9pCdkkWLUK4OZK6XS4mlTt.7Oy4poIdj88OiclyX.ey"
    },
    {
        "id": 8,
        "email": "thomas",
        "password": "$2a$08$n8SFGv88IFKDPC..Wbdr6eOJ7Rl0TvLukAOTFBtMAcXUt1hpYKS9i"
    },
    {
        "id": 9,
        "email": "testDemo",
        "password": "$2a$08$2OVzE0bt9e10lyeXOcGm2eqwwv7fujTWnT89imG4a0Bh7qYfu1Kku"
    },
    {
        "id": 10,
        "email": "te",
        "password": "$2a$08$y0JWXvzczxXQaunyiLcLJO7yOCj1xJF0dBsKY.fRxjNScfsLmVSBq"
    },
    {
        "id": 11,
        "email": "j",
        "password": "$2a$08$no/ted1Ll./OTw7xMLESEeE9wZZvRsM4r2vNbUSWkiGyweseHBlpy"
    },
    {
        "id": 12,
        "email": "z",
        "password": "$2a$08$7hlX1jei0PC9UgO94dPZC.3ROL/5hDsfjlElmSSfqT6ym4H3QGDQC"
    },
    {
        "id": 13,
        "email": "za",
        "password": "$2a$08$2VWKu5uuFgzzZP5eFjF4q.vgIZm9oQMj0QF9RMa9Y1ZppTZ.xhv3u"
    },
    {
        "id": 14,
        "email": "zaa",
        "password": "$2a$08$xXCDkrkF4P8HTGn9jB.3desI6CRMenTpUrSHQdLa7FZUG/d9Mem9m"
    },
    {
        "id": 15,
        "email": "zaa<",
        "password": "$2a$08$nofrUxLJ0mmd3RpxOsNxeOR9bluTBYnBl7LFvmr6LISIKwNT2sRlW"
    },
    {
        "id": 16,
        "email": "x",
        "password": "$2a$08$/RggqhE0D2g0GTatLv7BnOolOS3Rl0yqBljk4F3jY3tvLUaeSu5ty"
    },
    {
        "id": 17,
        "email": "xx",
        "password": "$2a$08$.6KjCWXmYUXyubKfsuPz5eNuyp2vuoXdFsv539KiQ2Xma2dR6zOku"
    },
    {
        "id": 18,
        "email": "sdas",
        "password": "$2a$08$76u09NlTYJGO3O/rEDcr7e5KoJJ4Dk0qndn/D7Ii3d6Ject4P5.8O"
    },
    {
        "id": 19,
        "email": "cvc",
        "password": "$2a$08$.q/TuRQfH1M9CxB82UOIFO0JNweWX/c.Mvildqe336gN/CUnVk2LC"
    },
    {
        "id": 20,
        "email": "dscvc",
        "password": "$2a$08$lfkPWjwqZJdQ6BTXtYJ07uwflmBUQeLs5OesQJ0FbgW9RbgAhrmi2"
    },
    {
        "id": 21,
        "email": "hghvghfj",
        "password": "$2a$08$KdzbfjbUP.vVR9xmDpTHHuKWa6AMPDnlPRop3oO1Ai.3bHX380lHa"
    },
    {
        "id": 22,
        "email": "hghvghfjss",
        "password": "$2a$08$OGBkCwTt7xMa3VAeVYTKNuUmhGiAkZsU6PZm4YiKBvUcKtjlwekCe"
    },
    {
        "id": 23,
        "email": "hghvghfjsss",
        "password": "$2a$08$Mfsuy0UR/S9TRuAf1FG.p.G0rojDx13J0AL00xv7b8vSv0tgoJI5y"
    },
    {
        "id": 24,
        "email": "dsadasxzxz",
        "password": "$2a$08$C.pYaByjmSZmfsHPuADLKe5bioz6BwkVHKjOfRuBMu7EtY8nKjXOu"
    },
    {
        "id": 25,
        "email": "papapa",
        "password": "$2a$08$oYp4ku55Ktc78gGNPWmqwuCXISluUZXtXBCe5vH6WCwUAHM5yyaK6"
    },
    {
        "id": 26,
        "email": "fdsfdsxzc",
        "password": "$2a$08$1r1igI/EuiQfWXBPd7XCyeEzz0JMs3cVk08jtI96WlQWfam9IvWF6"
    }
]